main.py
mcp_client_shell-0.2.dist-info/licenses/LICENSE
mcp_client_shell-0.2.dist-info/METADATA
mcp_client_shell-0.2.dist-info/WHEEL
mcp_client_shell-0.2.dist-info/entry_points.txt
mcp_client_shell-0.2.dist-info/top_level.txt
mcp_client_shell-0.2.dist-info/RECORD
