Metadata-Version: 2.4
Name: mcp-client-shell
Version: 0.2
Summary: A local MCP client for testing FastMCP servers
Author-email: Matheus Cafalchio <mcafalchio@gmail.com>
License: MIT
Requires-Python: >=3.13
License-File: LICENSE
Requires-Dist: fastmcp>=2.13.1
Dynamic: license-file
